{
	"__id": "b4cd7fbd-ce7e-4fbb-9f1e-f66473dccf6b",
	"active": true,
	"enabled": true,
	"code": "SqlDB",
	"name": "SqlDB",
	"type": {
		"code": "SqlDB"
	},
	"tool_Configs": [
		{
			"code": "create"
		},
		{
			"code": "database"
		},
		{
			"code": "database"
		},
		{
			"code": "database"
		},
		{
			"code": "server"
		},
		{
			"code": "server"
		},
		{
			"code": "server"
		},
		{
			"code": "port"
		},
		{
			"code": "port"
		},
		{
			"code": "port"
		},
		{
			"code": "username"
		},
		{
			"code": "username"
		},
		{
			"code": "username"
		},
		{
			"code": "password"
		},
		{
			"code": "password"
		},
		{
			"code": "password"
		},
		{
			"code": "connstr"
		},
		{
			"code": "connstr"
		},
		{
			"code": "connstr"
		},
		{
			"code": "type"
		},
		{
			"code": "type"
		},
		{
			"code": "type"
		}
	]
}